fairdetect_group_c/__init__.py
fairdetect_group_c/setup.py
fairdetectteamc-0.1.dist-info/LICENSE
fairdetectteamc-0.1.dist-info/METADATA
fairdetectteamc-0.1.dist-info/WHEEL
fairdetectteamc-0.1.dist-info/top_level.txt
fairdetectteamc-0.1.dist-info/RECORD
