Metadata-Version: 2.1
Name: fairdetectteamc
Version: 0.1
Summary: FairDetect class to detect bias, demonstrated by Team C. There are improvements included along with docstrings. 
Home-page: https://github.com/juliangaona/fairdetect_c
Author: Team_C_GMBD_2022_IE_UNIVERSITY
Author-email: julian.gaona.gonzalez@gmail.com
License: GNU General Public License v3.0 
Platform: UNKNOWN
License-File: LICENSE
